shangyu_pypi/__init__.py
shangyu_pypi-0.0.2.dist-info/METADATA
shangyu_pypi-0.0.2.dist-info/WHEEL
shangyu_pypi-0.0.2.dist-info/entry_points.txt
shangyu_pypi-0.0.2.dist-info/top_level.txt
shangyu_pypi-0.0.2.dist-info/RECORD
