Metadata-Version: 2.1
Name: shangyu-pypi
Version: 0.0.2
Summary: Test_Yu
Home-page: UNKNOWN
Author: ShangYu Chiang
Author-email: d07945011@ntu.edu.tw
License: UNKNOWN
Platform: UNKNOWN
Requires-Python: >=3.5
